{
  "id": "rich_text",
  "type": "SharedSlice",
  "name": "RichText",
  "description": "RichText",
  "variations": [
    {
      "id": "default",
      "name": "Default",
      "docURL": "...",
      "version": "initial",
      "description": "Default",
      "imageUrl": "",
      "primary": {
        "content": {
          "type": "StructuredText",
          "config": {
            "label": "Content",
            "placeholder": "",
            "allowTargetBlank": true,
            "multi": "paragraph,heading3,heading4,heading5,heading6,strong,em,hyperlink,list-item,o-list-item,image,embed,heading2,preformatted"
          }
        }
      },
      "items": {}
    }
  ]
}